native/wpihal/_init_robotpy_native_wpihal.py
native/wpihal/robotpy-native-wpihal.pc
native/wpihal/include/hal/.clang-tidy
native/wpihal/include/hal/Accelerometer.h
native/wpihal/include/hal/AddressableLED.h
native/wpihal/include/hal/AddressableLEDTypes.h
native/wpihal/include/hal/AnalogAccumulator.h
native/wpihal/include/hal/AnalogGyro.h
native/wpihal/include/hal/AnalogInput.h
native/wpihal/include/hal/AnalogOutput.h
native/wpihal/include/hal/AnalogTrigger.h
native/wpihal/include/hal/CAN.h
native/wpihal/include/hal/CANAPI.h
native/wpihal/include/hal/CANAPITypes.h
native/wpihal/include/hal/CTREPCM.h
native/wpihal/include/hal/ChipObject.h
native/wpihal/include/hal/Constants.h
native/wpihal/include/hal/Counter.h
native/wpihal/include/hal/DIO.h
native/wpihal/include/hal/DMA.h
native/wpihal/include/hal/DriverStation.h
native/wpihal/include/hal/DriverStationTypes.h
native/wpihal/include/hal/DutyCycle.h
native/wpihal/include/hal/Encoder.h
native/wpihal/include/hal/Errors.h
native/wpihal/include/hal/Extensions.h
native/wpihal/include/hal/FRCUsageReporting.h
native/wpihal/include/hal/HAL.h
native/wpihal/include/hal/HALBase.h
native/wpihal/include/hal/I2C.h
native/wpihal/include/hal/I2CTypes.h
native/wpihal/include/hal/Interrupts.h
native/wpihal/include/hal/LEDs.h
native/wpihal/include/hal/Main.h
native/wpihal/include/hal/Notifier.h
native/wpihal/include/hal/PWM.h
native/wpihal/include/hal/Ports.h
native/wpihal/include/hal/Power.h
native/wpihal/include/hal/PowerDistribution.h
native/wpihal/include/hal/REVPH.h
native/wpihal/include/hal/Relay.h
native/wpihal/include/hal/SPI.h
native/wpihal/include/hal/SPITypes.h
native/wpihal/include/hal/SerialPort.h
native/wpihal/include/hal/SimDevice.h
native/wpihal/include/hal/Threads.h
native/wpihal/include/hal/Types.h
native/wpihal/include/hal/UsageReporting.h
native/wpihal/include/hal/Value.h
native/wpihal/include/hal/cpp/SerialHelper.h
native/wpihal/include/hal/cpp/UnsafeDIO.h
native/wpihal/include/hal/cpp/fpga_clock.h
robotpy_native_wpihal-2025.3.2.dist-info/METADATA
robotpy_native_wpihal-2025.3.2.dist-info/WHEEL
robotpy_native_wpihal-2025.3.2.dist-info/entry_points.txt
robotpy_native_wpihal-2025.3.2.dist-info/RECORD
